MANIFEST.in
README.rst
setup.py
django_template_media/__init__.py
django_template_media/context_processors.py
django_template_media.egg-info/PKG-INFO
django_template_media.egg-info/SOURCES.txt
django_template_media.egg-info/dependency_links.txt
django_template_media.egg-info/not-zip-safe
django_template_media.egg-info/requires.txt
django_template_media.egg-info/top_level.txt
django_template_media/templatetags/__init__.py
django_template_media/templatetags/media_tags.py