Metadata-Version: 1.1
Name: django-template-media
Version: 0.2.0
Summary: Simple tools to extend the django admin site
Home-page: https://bitbucket.org/tim_heap/django-template-media
Author: Tim Heap
Author-email: tim@ionata.com.au
License: UNKNOWN
Platform: UNKNOWN
Classifier: Environment :: Web Environment
Classifier: Intended Audience :: Developers
Classifier: Operating System :: OS Independent
Classifier: Programming Language :: Python
Classifier: Framework :: Django
